sussy/__init__.py
sussy/characters.py
sussy-0.1.3.dist-info/LICENSE
sussy-0.1.3.dist-info/METADATA
sussy-0.1.3.dist-info/WHEEL
sussy-0.1.3.dist-info/top_level.txt
sussy-0.1.3.dist-info/RECORD
