Metadata-Version: 2.1
Name: sussy
Version: 0.1.3
Summary: when the python developer is sus
Home-page: https://github.com/ActuallyFlamey/sussy/
Author: Flamey
Author-email: morellialex08@gmail.com
License: UNKNOWN
Download-URL: https://github.com/ActuallyFlamey/sussy/archive/refs/tags/0.1.0.tar.gz
Platform: UNKNOWN
License-File: LICENSE
